geoyolo/__init__.py
geoyolo/cli.py
geoyolo/core/__init__.py
geoyolo/core/inference.py
geoyolo/core/utils.py
geoyolo-0.1.0.dist-info/licenses/LICENSE
venv/bin/gdal2tiles.py
venv/bin/gdal2xyz.py
venv/bin/gdal_calc.py
venv/bin/gdal_edit.py
venv/bin/gdal_fillnodata.py
venv/bin/gdal_merge.py
venv/bin/gdal_pansharpen.py
venv/bin/gdal_polygonize.py
venv/bin/gdal_proximity.py
venv/bin/gdal_retile.py
venv/bin/gdal_sieve.py
venv/bin/gdalattachpct.py
venv/bin/gdalcompare.py
venv/bin/gdalmove.py
venv/bin/ogr_layer_algebra.py
venv/bin/ogrmerge.py
venv/bin/pct2rgb.py
venv/bin/rgb2pct.py
geoyolo-0.1.0.dist-info/METADATA
geoyolo-0.1.0.dist-info/WHEEL
geoyolo-0.1.0.dist-info/entry_points.txt
geoyolo-0.1.0.dist-info/top_level.txt
geoyolo-0.1.0.dist-info/RECORD
